[
  {
    "id": "step-configuration",
    "title": "Step Configuration", 
    "description": "All steps should have a defined configuration, this is how you define the step's behavior and how it will be triggered.",
    "lines": [
      "2"
    ]
  },
  {
    "id": "api-configuration",
    "title": "DELETE API Step",
    "description": "Definition of a DELETE API endpoint for soft deleting a pet",
    "lines": [
      "2"
    ]
  },
  {
    "id": "async-handler",
    "title": "Async Handler",
    "description": "Python handlers are async functions that can handle asynchronous operations",
    "lines": [
      "4"
    ]
  },
  {
    "id": "context-extraction",
    "title": "Context Extraction",
    "description": "Extract logger and emit functions from the context safely",
    "lines": [
      "5-6"
    ]
  },
  {
    "id": "module-imports",
    "title": "Module Imports",
    "description": "Dynamic import of the pet store module with error handling",
    "lines": [
      "8-15"
    ]
  },
  {
    "id": "path-parameters",
    "title": "Path Parameters",
    "description": "Using path parameters to capture the pet ID from the URL",
    "lines": [
      "17"
    ]
  },
  {
    "id": "soft-deletion",
    "title": "Soft Deletion",
    "description": "Perform a soft delete instead of permanent removal, scheduling the pet for purging",
    "lines": [
      "18"
    ]
  },
  {
    "id": "conditional-response",
    "title": "Conditional Response",
    "description": "Return different responses based on whether the deletion was successful",
    "lines": [
      "20-21"
    ]
  },
  {
    "id": "event-driven-architecture",
    "title": "Emits",
    "description": "Emit events when a pet is soft deleted to trigger background cleanup processes",
    "lines": [
      "2",
      "30-38"
    ]
  },
  {
    "id": "handler",
    "title": "Handler",
    "description": "The handler function that executes when the DELETE request is made",
    "lines": [
      "4-47"
    ]
  },
  {
    "id": "logger",
    "title": "Logger",
    "description": "Log the soft deletion with details about the purge schedule",
    "lines": [
      "23-28"
    ]
  },
  {
    "id": "http-response",
    "title": "HTTP Response",
    "description": "Returns appropriate HTTP status codes: 202 for accepted, 404 for not found",
    "lines": [
      "40-47"
    ]
  }
]

